tarentula/__init__.py
tarentula/aggregate.py
tarentula/cli.py
tarentula/command.py
tarentula/config_file_reader.py
tarentula/count.py
tarentula/datashare_client.py
tarentula/download.py
tarentula/export_by_query.py
tarentula/graph_realtime.py
tarentula/logger.py
tarentula/metadata_fields.py
tarentula/tag_cleaning_by_query.py
tarentula/tagging.py
tarentula/tagging_by_query.py
tarentula-4.4.0.dist-info/LICENSE
tarentula-4.4.0.dist-info/METADATA
tarentula-4.4.0.dist-info/WHEEL
tarentula-4.4.0.dist-info/entry_points.txt
tarentula-4.4.0.dist-info/RECORD
