Metadata-Version: 2.1
Name: tarentula
Version: 4.4.0
Summary: 
Author: ICIJ
Author-email: engineering@icij.org
Requires-Python: >=3.8,<4.0
Classifier: Programming Language :: Python :: 3
Classifier: Programming Language :: Python :: 3.8
Classifier: Programming Language :: Python :: 3.9
Classifier: Programming Language :: Python :: 3.10
Classifier: Programming Language :: Python :: 3.11
Requires-Dist: click (>=8.1,<9.0)
Requires-Dist: coloredlogs (==14.0)
Requires-Dist: pyyaml (>=6.0.1,<7.0.0)
Requires-Dist: requests (>=2.28,<3.0)
Requires-Dist: rich (>=12,<13)
